{
    "version": "5.8.1",
    "flags": {},
    "shapes": [
        {
            "label": "haru",
            "points": [
                [
                    1428.5531914893618,
                    1378.723404255319
                ],
                [
                    1747.7021276595744,
                    1630.851063829787
                ]
            ],
            "group_id": null,
            "description": "",
            "shape_type": "rectangle",
            "flags": {},
            "mask": null
        },
        {
            "label": "haru",
            "points": [
                [
                    1457.276595744681,
                    1648.9361702127658
                ],
                [
                    1750.8936170212767,
                    1902.127659574468
                ]
            ],
            "group_id": null,
            "description": "",
            "shape_type": "rectangle",
            "flags": {},
            "mask": null
        },
        {
            "label": "haru",
            "points": [
                [
                    972.1702127659576,
                    1423.404255319149
                ],
                [
                    1214.723404255319,
                    1632.978723404255
                ]
            ],
            "group_id": null,
            "description": "",
            "shape_type": "rectangle",
            "flags": {},
            "mask": null
        },
        {
            "label": "haru",
            "points": [
                [
                    1157.276595744681,
                    1426.5957446808509
                ],
                [
                    1400.8936170212767,
                    1626.5957446808509
                ]
            ],
            "group_id": null,
            "description": "",
            "shape_type": "rectangle",
            "flags": {},
            "mask": null
        }
    ],
    "imagePath": "haru_067.jpg",
    "imageHeight": 4096,
    "imageWidth": 3072
}